pnwapi/__init__.py
pnwapi/exceptions.py
pnwapi/models/__init__.py
pnwapi/models/alliance.py
pnwapi/models/city.py
pnwapi/models/color.py
pnwapi/models/model_enums.py
pnwapi/models/nation.py
pnwapi/models/treaty.py
pnwapi/pnwapi.py
pnwapi-0.1.3.dist-info/LICENSE.md
pnwapi-0.1.3.dist-info/WHEEL
pnwapi-0.1.3.dist-info/METADATA
pnwapi-0.1.3.dist-info/RECORD
