Metadata-Version: 2.1
Name: pnwapi
Version: 0.1.3
Summary: 
Home-page: https://github.com/Cikmo/pnwapi
Keywords: api,pnw,politics and war,pnwkit,wrapper
Author: Christian
Author-email: 59421913+Cikmo@users.noreply.github.com
Requires-Python: >=3.10,<4.0
Classifier: Programming Language :: Python :: 3
Classifier: Programming Language :: Python :: 3.10
Classifier: Programming Language :: Python :: 3.11
Requires-Dist: asyncpg (>=0.26.0,<0.27.0)
Requires-Dist: pnwkit-py (>=2.5.6,<3.0.0)
Requires-Dist: tortoise-orm (>=0.19.2,<0.20.0)
Project-URL: Documentation, https://pnwapi.readthedocs.io/en/latest/
Project-URL: Repository, https://github.com/Cikmo/pnwapi
